<annotation>
  <folder>images</folder>
  <filename>2020(347).jpg</filename>
  <source>
    <database>Unknown</database>
  </source>
  <size>
    <width>1920</width>
    <height>1080</height>
    <depth>3</depth>
  </size>
  <segmented>0</segmented>
  <object>
    <name>Electric-bicycle</name>
    <pose>Unspecified</pose>
    <truncated>0</truncated>
    <difficult>0</difficult>
    <bndbox>
      <xmin>994</xmin>
      <ymin> 482</ymin>
      <xmax> 1771 </xmax>
      <ymax>1080</ymax>
    </bndbox>
  </object>
</annotation>